requirements.txt
setup.py
django_loadsql/__init__.py
django_loadsql/__main__.py
django_loadsql.egg-info/PKG-INFO
django_loadsql.egg-info/SOURCES.txt
django_loadsql.egg-info/dependency_links.txt
django_loadsql.egg-info/requires.txt
django_loadsql.egg-info/top_level.txt
django_loadsql/management/__init__.py
django_loadsql/management/commands/__init__.py
django_loadsql/management/commands/loadsql.py