Metadata-Version: 2.1
Name: django-loadsql
Version: 2020.7.1
Summary: load sql file(s)
Home-page: https://github.com/andrewp-as-is/django-loadsql.py
License: Unlicense
Keywords: django load sql
Platform: UNKNOWN
Classifier: Framework :: Django
Classifier: License :: Public Domain
Classifier: Operating System :: OS Independent
Classifier: Programming Language :: Python :: 3
